class_exercise_basic_vhdl/solution_basic_vhdl/serializer.vhd
-- Serializer
library ieee; use ieee.std_logic_1164.all;

-- Given the start command, serialize the input data_in to the output, adding
-- a start bit at 1 and a stop bit at 0. Set busy to 1 during serialization
entity serializer is
  port (
    clk, res : in std_logic;
    start : in std_logic;
    data_in : in std_logic_vector( 3 downto 0 );
    serial_out : out std_logic;
    busy : out std_logic
  );
end entity serializer;

architecture behavioral of serializer is

  -- State. The start bit is sent directly during the idle state if the start
  -- command is asserted, bit0-bit3 place the correct bit to the output,
  -- send_stop is used to send the stop bit
  type stato is (idle, bit0, bit1, bit2, bit3, send_stop);
  signal present_state : stato;

begin
  
  -- Sequential process. Update the present state directly
  seq: process (res, clk) is begin

    if res = '0' then
      present_state <= idle;
    elsif rising_edge(clk) then

      case present_state is
        when idle =>
          if start = '1' then present_state <= bit0;
          end if;
        when bit0 => present_state <= bit1;
        when bit1 => present_state <= bit2;
        when bit2 => present_state <= bit3;
        when bit3 => present_state <= send_stop;
        when send_stop => present_state <= idle;
      end case;

    end if;
  end process seq;

  -- Output process.
  uscite: process (present_state, start, data_in) is begin

    -- By default, we are not serializing, busy is off and serial_out is at the
    -- default 0 value
    busy <= '0';
    serial_out <= '0';
    -- Update the output according to the present state
    case present_state is
      when idle =>
        if start = '1' then
          -- Output the start bit
          serial_out <= '1';
          -- Handle the busy signal
          -- Case 1: we set busy to '1' immediately. This generates a 0 delay
          -- combinational cycle with the recognizer, and simulation does not
          -- proceed
          busy <= '1';

          -- Case 2: we assume there is some delay in setting busy due to the
          -- logic. There still is a combinational cycle, but not a 0 delay.
          -- Simulation proceeds, but outcome is not always correct
          -- busy <= '1' after 1 ns;
          -- Different delays give different results
          -- busy <= '1' after 1.6 ns;

          -- Case 3: we wait the next cycle before setting busy to '1'. This
          -- avoids the combinational cycle, since the serializer is no longer
          -- a Mealy machine
          -- busy <= '0';
        end if;
      when bit0 => serial_out <= data_in( 0 ); busy <= '1';
      when bit1 => serial_out <= data_in( 1 ); busy <= '1';
      when bit2 => serial_out <= data_in( 2 ); busy <= '1';
      when bit3 => serial_out <= data_in( 3 ); busy <= '1';
      when send_stop => serial_out <= '0'; busy <= '1';
    end case;

  end process uscite;

end architecture behavioral;

class_exercise_basic_vhdl/solution_basic_vhdl/test_serializer.vhd
library ieee; use ieee.std_logic_1164.all;

entity test_serializer is
end entity;

architecture behavioral of test_serializer is

  component serializer is
    port (
      clk, res : in std_logic;
      start : in std_logic;
      data_in : in std_logic_vector( 3 downto 0 );
      serial_out : out std_logic;
      busy : out std_logic
    );
  end component serializer;

  signal clk, res : std_logic;
  signal start : std_logic;
  signal data_in : std_logic_vector( 3 downto 0 );
  signal serial_out : std_logic;
  signal busy : std_logic;

begin

  -- Instantiate the device under test
  dut : serializer port map (
    clk => clk,
    res => res,
    start => start,
    data_in => data_in,
    serial_out => serial_out,
    busy => busy
  );

  -- Clock process
  process is begin
    clk <= '1'; wait for 5 ns;
    clk <= '0'; wait for 5 ns;
  end process;

  -- Reset process
  process is begin
    res <= '0'; wait for 100 ns;
    res <= '1';
    wait;
  end process;

  -- Input process. We set the input data, then set start to '1' for one clock
  -- cycle, then wait 10 more cycle and set start to '1' again
  process is begin
    data_in <= "0101";
    start <= '0';
    wait for 100 ns;
    wait for 31 ns;
    start <= '1';
    wait for 10 ns;
    start <= '0';
    wait for 100 ns;
    start <= '1';
    wait for 100 ns;
    wait;
  end process;

end architecture;

class_exercise_basic_vhdl/solution_basic_vhdl/waveform_serializer.vcd
$date
  Fri Mar 14 08:59:49 2025
$end
$version
  GHDL v0
$end
$timescale
  1 fs
$end
$scope module standard $end
$upscope $end
$scope module std_logic_1164 $end
$upscope $end
$scope module test_serializer $end
$var reg 1 ! clk $end
$var reg 1 " res $end
$var reg 1 # start $end
$var reg 4 $ data_in[3:0] $end
$var reg 1 % serial_out $end
$var reg 1 & busy $end
$scope module dut $end
$var reg 1 ' clk $end
$var reg 1 ( res $end
$var reg 1 ) start $end
$var reg 4 * data_in[3:0] $end
$var reg 1 + serial_out $end
$var reg 1 , busy $end
$comment present_state is not handled $end
$upscope $end
$upscope $end
$enddefinitions $end
#0
1!
0"
0#
b0101 $
0%
0&
1'
0(
0)
b0101 *
0+
0,
#5000000
0!
0'
#10000000
1!
1'
#15000000
0!
0'
#20000000
1!
1'
#25000000
0!
0'
#30000000
1!
1'
#35000000
0!
0'
#40000000
1!
1'
#45000000
0!
0'
#50000000
1!
1'
#55000000
0!
0'
#60000000
1!
1'
#65000000
0!
0'
#70000000
1!
1'
#75000000
0!
0'
#80000000
1!
1'
#85000000
0!
0'
#90000000
1!
1'
#95000000
0!
0'
#100000000
1!
1"
1'
1(
#105000000
0!
0'
#110000000
1!
1'
#115000000
0!
0'
#120000000
1!
1'
#125000000
0!
0'
#130000000
1!
1'
#131000000
1#
1%
1&
1)
1+
1,
#135000000
0!
0'
#140000000
1!
1'
1+
1,
#141000000
0#
0)
1+
1,
#145000000
0!
0'
#150000000
1!
0%
1'
0+
1,
#155000000
0!
0'
#160000000
1!
1%
1'
1+
1,
#165000000
0!
0'
#170000000
1!
0%
1'
0+
1,
#175000000
0!
0'
#180000000
1!
1'
1,
#185000000
0!
0'
#190000000
1!
0&
1'
0,
#195000000
0!
0'
#200000000
1!
1'
#205000000
0!
0'
#210000000
1!
1'
#215000000
0!
0'
#220000000
1!
1'
#225000000
0!
0'
#230000000
1!
1'
#235000000
0!
0'
#240000000
1!
1'
#241000000
1#
1%
1&
1)
1+
1,
#245000000
0!
0'
#250000000
1!
1'
1+
1,
#255000000
0!
0'
#260000000
1!
0%
1'
0+
1,
#265000000
0!
0'
#270000000
1!
1%
1'
1+
1,
#275000000
0!
0'
#280000000
1!
0%
1'
0+
1,
#285000000
0!
0'
#290000000
1!
1'
1,
#295000000
0!
0'
#300000000
1!
1%
1'
1+
1,
#305000000
0!
0'
#310000000
1!
1'
1+
1,
#315000000
0!
0'
#320000000
1!
0%
1'
0+
1,
#325000000
0!
0'
#330000000
1!
1%
1'
1+
1,
#335000000
0!
0'
#340000000
1!
0%
1'
0+
1,
#341000000
#345000000
0!
0'
#350000000
1!
1'
1,
#355000000
0!
0'
#360000000
1!
1%
1'
1+
1,
#365000000
0!
0'
#370000000
1!
1'
1+
1,
#375000000
0!
0'
#380000000
1!
0%
1'
0+
1,
#385000000
0!
0'
#390000000
1!
1%
1'
1+
1,
#395000000
0!
0'
#400000000
1!
0%
1'
0+
1,
#405000000
0!
0'
#410000000
1!
1'
1,
#415000000
0!
0'
#420000000
1!
1%
1'
1+
1,
#425000000
0!
0'
#430000000
1!
1'
1+
1,
#435000000
0!
0'
#440000000
1!
0%
1'
0+
1,
#445000000
0!
0'
#450000000
1!
1%
1'
1+
1,
#455000000
0!
0'
#460000000
1!
0%
1'
0+
1,
#465000000
0!
0'
#470000000
1!
1'
1,
#475000000
0!
0'
#480000000
1!
1%
1'
1+
1,
#485000000
0!
0'
#490000000
1!
1'
1+
1,
#495000000
0!
0'
#500000000
1!
0%
1'
0+
1,
