class_exercise_basic_vhdl/solution_basic_vhdl/recognizer.vhd
-- Sequence recognizer
library ieee; use ieee.std_logic_1164.all;

-- Recognizes the sequence 1101 at the input. Once the sequence is received,
-- puts start to 1 unless busy is 1
entity recognizer is
  port (
    clk, res : in std_logic;
    command : in std_logic;
    start : out std_logic;
    busy : in std_logic
  );
end entity recognizer;

architecture behavioral of recognizer is

  -- State. State a is the idle state. States b, c and d are used to recognize
  -- the input sequence
  type stato is (a, b, c, d);
  signal present_state : stato;

begin
  
  -- Sequential process. Determine the next state by updating directly the
  -- present state
  seq: process (res, clk) is begin

    -- Check for reset.
    if res = '0' then
      -- Go to the initial state
      present_state <= a;

    elsif rising_edge(clk) then
      -- Update the present state at the clock edge, depending on the current
      -- state and the input value
      case present_state is

        when a =>
          if command = '1' then present_state <= b;
          end if;

        when b =>
          if command = '0' then present_state <= a;
          else present_state <= c;
          end if;

        when c =>
          if command = '0' then present_state <= d;
          end if;

        when d =>
          if ( command = '0' or (command = '1' and busy = '0') ) then present_state <= a;
          end if;

      end case;

    end if;
  end process seq;

  -- Output process. The start command is activated only if we have recognized
  -- the input sequence (we are in state d) the input is the last bit of the
  -- correct sequence (command = '1') and the serializer is not busy (busy = '0')
  uscite: process (present_state, command, busy) is begin

    start <= '0';
    if present_state = d and command = '1' and busy = '0' then
      -- Start is always set immediately state d if command is 1 and busy is 0
      start <= '1';
      -- Case 2: we assume there is some delay in setting start, compared to busy
      -- start <= '1' after 1 ns;
    end if;

  end process uscite;

end architecture behavioral;

class_exercise_basic_vhdl/solution_basic_vhdl/test_recognizer.vhd
-- Sequence recognizer
library ieee; use ieee.std_logic_1164.all;

entity test_recognizer is
end entity;

architecture behavioral of test_recognizer is

  component recognizer is
    port (
      clk, res : in std_logic;
      command : in std_logic;
      start : out std_logic;
      busy : in std_logic
    );
  end component recognizer;

  signal clk, res : std_logic;
  signal command : std_logic;
  signal start : std_logic;
  signal busy : std_logic;

begin
  -- Instanzia il componente da testare
  dut : recognizer port map (
    clk => clk,
    res => res,
    command => command,
    start => start,
    busy => busy
  );

  -- Clock process
  process is begin
    clk <= '1'; wait for 5 ns;
    clk <= '0'; wait for 5 ns;
  end process;

  -- Reset process
  process is begin
    res <= '0'; wait for 100 ns;
    res <= '1';
    wait;
  end process;

  -- Input process. We set busy initially to 0, then we send a sequence on
  -- command. The sequence is "1011010110111100000". The correct "1101" sequence
  -- appears twice
  process is begin
    command <= '0';
    busy <= '0';
    wait for 100 ns;
    wait for 21 ns;
    -- Send '1'
    command <= '1';
    wait for 10 ns;
    -- Send '0'
    command <= '0';
    wait for 10 ns;
    -- Send '11' (notice we wait 20 ns, not 10!)
    command <= '1';
    wait for 20 ns;
    -- Send '0'
    command <= '0';
    wait for 10 ns;
    -- Send '1'
    command <= '1';
    wait for 10 ns;
    -- Send '0'
    command <= '0';
    wait for 10 ns;
    -- Set busy to '1'
    busy <= '1';
    -- Send '11'
    command <= '1';
    wait for 20 ns;
    -- Send '0'
    command <= '0';
    wait for 10 ns;
    -- Send '1111' (we wait 30 ns, and another 10 ns after we set busy to '0')
    command <= '1';
    wait for 30 ns;
    busy <= '0';
    wait for 10 ns;
    -- Send '00000'
    command <= '0';
    wait for 50 ns;
    wait;
  end process;

end architecture;

class_exercise_basic_vhdl/solution_basic_vhdl/waveform_recognizer.vcd
$date
  Fri Mar 14 08:59:12 2025
$end
$version
  GHDL v0
$end
$timescale
  1 fs
$end
$scope module standard $end
$upscope $end
$scope module std_logic_1164 $end
$upscope $end
$scope module test_recognizer $end
$var reg 1 ! clk $end
$var reg 1 " res $end
$var reg 1 # command $end
$var reg 1 $ start $end
$var reg 1 % busy $end
$scope module dut $end
$var reg 1 & clk $end
$var reg 1 ' res $end
$var reg 1 ( command $end
$var reg 1 ) start $end
$var reg 1 * busy $end
$comment present_state is not handled $end
$upscope $end
$upscope $end
$enddefinitions $end
#0
1!
0"
0#
0$
0%
1&
0'
0(
0)
0*
#5000000
0!
0&
#10000000
1!
1&
#15000000
0!
0&
#20000000
1!
1&
#25000000
0!
0&
#30000000
1!
1&
#35000000
0!
0&
#40000000
1!
1&
#45000000
0!
0&
#50000000
1!
1&
#55000000
0!
0&
#60000000
1!
1&
#65000000
0!
0&
#70000000
1!
1&
#75000000
0!
0&
#80000000
1!
1&
#85000000
0!
0&
#90000000
1!
1&
#95000000
0!
0&
#100000000
1!
1"
1&
1'
#105000000
0!
0&
#110000000
1!
1&
#115000000
0!
0&
#120000000
1!
1&
#121000000
1#
1(
#125000000
0!
0&
#130000000
1!
1&
#131000000
0#
0(
#135000000
0!
0&
#140000000
1!
1&
#141000000
1#
1(
#145000000
0!
0&
#150000000
1!
1&
#155000000
0!
0&
#160000000
1!
1&
#161000000
0#
0(
#165000000
0!
0&
#170000000
1!
1&
#171000000
1#
1$
1(
1)
#175000000
0!
0&
#180000000
1!
0$
1&
0)
#181000000
0#
0(
#185000000
0!
0&
#190000000
1!
1&
#191000000
1#
1%
1(
1*
#195000000
0!
0&
#200000000
1!
1&
#205000000
0!
0&
#210000000
1!
1&
#211000000
0#
0(
#215000000
0!
0&
#220000000
1!
1&
#221000000
1#
1(
#225000000
0!
0&
#230000000
1!
1&
#235000000
0!
0&
#240000000
1!
1&
#245000000
0!
0&
#250000000
1!
1&
#251000000
1$
0%
1)
0*
#255000000
0!
0&
#260000000
1!
0$
1&
0)
#261000000
0#
0(
