class_exercise_basic_vhdl/serializer.vhd
--serializer

library IEEE;
use IEEE.STD_LOGIC_1164.ALL;

entity serializer is
    Port ( clk          :       in  STD_LOGIC;
           reset        :       in  STD_LOGIC;
           start        :       in  STD_LOGIC;
           data_in      :       in STD_LOGIC_VECTOR(3 downto 0);
           busy         :       out STD_LOGIC;
           serial_out   :       out STD_LOGIC
    );
end serializer;

architecture behavioral of serializer is
    type states is (idle,S0,S1,S2,S3,S4);
    signal present_state,next_state:states;
begin
    process (clk,reset) begin
        if reset='1' then
            present_state<=idle;
        elsif rising_edge(clk) then
            present_state<=next_state;
        end if;
    end process;
    process(present_state,start) begin
        case present_state is
            when idle =>
                if start='1' then
                    next_state<=S0;
                else
                    next_state<=idle;
                end if;
            when S0 =>
                next_state<=S1;
            when S1 =>
                next_state<=S2;
            when S2 =>
                next_state<=S3;
            when S3 =>
                next_state<=S4;
            when S4 =>
                next_state<=idle;
        end case;
    end process;
    process(present_state,start) begin
        busy<='0';
        serial_out<='0';
        case present_state is 
            when idle=>
                busy <= '0';
                serial_out <= '0';
                if start='1' then 
                    busy<='1';
                    serial_out<='1';
                end if;
            when S0=>
                    busy<='1';
                    serial_out<=data_in(0);
            when S1=>
                    busy<='1';
                    serial_out<=data_in(1);
            when S2=>
                    busy<='1';
                    serial_out<=data_in(2);
            when S3=>
                    busy<='1';
                    serial_out<=data_in(3);
            when S4=>
                    busy<='1';
                    serial_out<='0';

        end case;
    end process;
end behavioral;

class_exercise_basic_vhdl/serializer_tb.vhd
--serializer_tb
library IEEE;
use IEEE.STD_LOGIC_1164.ALL;
entity serializer_tb is
end serializer_tb;

architecture simple of serializer_tb is
    signal clk : std_logic := '0';
    signal reset : std_logic := '0';
    signal start : std_logic := '0';
    signal data_in : std_logic_vector(3 downto 0) := (others => '0');
    signal busy : std_logic := '0';
    signal serial_out : std_logic := '0';
    begin
    g1: entity work.serializer 
        port map(clk => clk, reset => reset, start => start, data_in => data_in, busy => busy, serial_out => serial_out);
    clk <= not clk after 10 ns;
    reset<= '0';
    start<= '0', '1' after 40 ns, '0' after 60 ns;
    data_in<= "0000", "1011" after  50 ns, "0000" after 150 ns;
end simple;

class_exercise_basic_vhdl/elaborated_benches_waveform/waveform_serializer.vcd
$date
  Thu Mar 13 10:24:37 2025
$end
$version
  GHDL v0
$end
$timescale
  1 fs
$end
$scope module standard $end
$upscope $end
$scope module std_logic_1164 $end
$upscope $end
$scope module serializer_tb $end
$var reg 1 ! clk $end
$var reg 1 " reset $end
$var reg 1 # start $end
$var reg 4 $ data_in[3:0] $end
$var reg 1 % busy $end
$var reg 1 & serial_out $end
$scope module g1 $end
$var reg 1 ' clk $end
$var reg 1 ( reset $end
$var reg 1 ) start $end
$var reg 4 * data_in[3:0] $end
$var reg 1 + busy $end
$var reg 1 , serial_out $end
$comment present_state is not handled $end
$comment next_state is not handled $end
$upscope $end
$upscope $end
$enddefinitions $end
#0
0!
0"
0#
b0000 $
0%
0&
0'
0(
0)
b0000 *
0+
0,
#10000000
1!
1'
#20000000
0!
0'
#30000000
1!
1'
#40000000
0!
1#
1%
1&
0'
1)
1+
1,
#50000000
1!
b0001 $
1'
b0001 *
1+
1,
#60000000
0!
0#
0'
0)
1+
1,
#70000000
1!
b0011 $
1'
b0011 *
1+
1,
#80000000
0!
0'
#90000000
1!
0&
1'
1+
0,
#100000000
0!
0'
#110000000
1!
b1011 $
1&
1'
b1011 *
1+
1,
#120000000
0!
0'
#130000000
1!
b0000 $
0&
1'
b0000 *
1+
0,
#140000000
0!
0'
#150000000
1!
0%
1'
0+
